drf_accelerator/__init__.py
drf_accelerator/drf_accelerator.cpython-313-x86_64-linux-gnu.so
drf_accelerator/mixins.py
drf_accelerator-0.1.0a1.dist-info/METADATA
drf_accelerator-0.1.0a1.dist-info/WHEEL
drf_accelerator-0.1.0a1.dist-info/licenses/LICENSE
drf_accelerator-0.1.0a1.dist-info/RECORD
