Metadata-Version: 2.4
Name: drf-accelerator
Version: 0.1.0a1
Classifier: Framework :: Django
Classifier: Programming Language :: Python :: 3 :: Only
Classifier: Programming Language :: Python :: 3.10
Classifier: Programming Language :: Python :: 3.11
Classifier: Programming Language :: Python :: 3.12
Classifier: Programming Language :: Python :: 3.13
Classifier: Programming Language :: Python :: 3.14
Classifier: Programming Language :: Python :: Implementation :: CPython
Classifier: Programming Language :: Python :: Implementation :: PyPy
Classifier: Programming Language :: Rust
Classifier: Topic :: Software Development :: Libraries :: Python Modules
Requires-Dist: djangorestframework>=3.12
License-File: LICENSE
Summary: A high-performance Rust-backed accelerator for Django Rest Framework.
License: MIT
Requires-Python: >=3.10
